{
  "$schema": "https://json-schema.org/draft/2020-12/schema",
  "$id": "https://karanga.dev/spec/0.1/type-descriptor.schema.json",
  "title": "Karanga Type Descriptor",
  "description": "Describes a node type's shape (format-v0.1 §6.3). Used for base-schema types and for custom types declared in manifest.types.",
  "type": "object",
  "required": ["content"],
  "additionalProperties": false,
  "properties": {
    "content": {
      "enum": ["empty", "inline", "raw"],
      "description": "The node's own payload kind."
    },
    "children": {
      "description": "Allowed child types; presence makes the type a container.",
      "oneOf": [
        { "const": "block" },
        {
          "type": "array",
          "items": { "type": "string" },
          "minItems": 1
        }
      ]
    },
    "attrs": {
      "type": "object",
      "description": "Permitted attributes and their value domains (no-float domain, §9.1)."
    },
    "render": {
      "type": "object",
      "description": "Advisory render hints; the format never depends on them."
    }
  }
}
